{ "columns":16,
 "image":"..\/PNG\/006_Nature.png",
 "imageheight":256,
 "imagewidth":256,
 "margin":0,
 "name":"006_Nature",
 "spacing":0,
 "tilecount":256,
 "tiledversion":"1.7.2",
 "tileheight":16,
 "tiles":[
        {
         "id":0,
         "properties":[
                {
                 "name":"BURNABLE",
                 "type":"string",
                 "value":""
                }, 
                {
                 "name":"C_0_DESCRIPTION",
                 "type":"string",
                 "value":"jolndxoidjn"
                }, 
                {
                 "name":"C_12_ATLAS_INDEX",
                 "type":"string",
                 "value":"Nature_0_0"
                }, 
                {
                 "name":"C_1_IS_WALKABLE",
                 "type":"bool",
                 "value":false
                }, 
                {
                 "name":"C_3_LAYER",
                 "type":"string",
                 "value":"MEAT_INTERACTABLE"
                }, 
                {
                 "name":"C_4_MAGIC_NOISE",
                 "type":"int",
                 "value":0
                }, 
                {
                 "name":"C_57_HITPOINTS",
                 "type":"int",
                 "value":10
                }, 
                {
                 "name":"C_5_MATRIX_NOISE",
                 "type":"int",
                 "value":0
                }, 
                {
                 "name":"C_67_SURFACE_PROPERTIES",
                 "type":"string",
                 "value":"1:3"
                }, 
                {
                 "name":"C_6_NAME",
                 "type":"string",
                 "value":"saffga<"
                }, 
                {
                 "name":"C_7_STATIC_TILESET_NR",
                 "type":"int",
                 "value":0
                }, 
                {
                 "name":"ENFLAMEABLE",
                 "type":"string",
                 "value":""
                }, 
                {
                 "name":"F_1_INTERACTABLE_TYPE",
                 "type":"bool",
                 "value":false
                }],
         "type":"INTERACTABLE_ENTITY"
        }],
 "tilewidth":16,
 "type":"tileset",
 "version":"1.6"
}